README.md
setup.cfg
setup.py
sync.py
classes/__init__.py
classes/fileinfo.py
classes/glacync.py
glacier_backup_sync.egg-info/PKG-INFO
glacier_backup_sync.egg-info/SOURCES.txt
glacier_backup_sync.egg-info/dependency_links.txt
glacier_backup_sync.egg-info/entry_points.txt
glacier_backup_sync.egg-info/requires.txt
glacier_backup_sync.egg-info/top_level.txt