Metadata-Version: 1.2
Name: glacier-backup-sync
Version: 1.2.3
Summary: This package provides the command "glacier_sync".
Home-page: https://git.smartfactory.ch/smartfactory-public/python-glacier-sync
Author: Stefan Schärmeli
Author-email: schaermu@smartfactory.ch
License: UNKNOWN
Download-URL: https://git.smartfactory.ch/smartfactory-public/python-glacier-sync/repository/
Keywords: backup,glacier,cli
Platform: UNKNOWN
Requires-Python: >3.5.1
